MBCalculator/Calc.py
MBCalculator/__init__.py
MBCalculator-0.0.2.dist-info/LICENCE
MBCalculator-0.0.2.dist-info/METADATA
MBCalculator-0.0.2.dist-info/WHEEL
MBCalculator-0.0.2.dist-info/top_level.txt
MBCalculator-0.0.2.dist-info/RECORD
